jtimer/__init__.py
jtimer/controller/__init__.py
jtimer/controller/calc_utils.py
jtimer/controller/timer_controller.py
jtimer/dao/__init__.py
jtimer/main.py
jtimer/model/__init__.py
jtimer/model/time_event.py
jtimer/model/timer.py
jtimer/view/__init__.py
jtimer/view/stats_view.py
jtimer/view/timer_widget.py
jtimer/view/timers_view.py
jtimer-0.1.5.dist-info/entry_points.txt
jtimer-0.1.5.dist-info/WHEEL
jtimer-0.1.5.dist-info/METADATA
jtimer-0.1.5.dist-info/RECORD
